pynep_cpu.dylibs/libomp.dylib
pynep_cpu/_version.py
pynep_cpu/nep_cpu.cpython-38-darwin.so
pynep_cpu/calculator.py
pynep_cpu/structure.py
pynep_cpu/ptable.json
pynep_cpu-0.1.dev9.dist-info/RECORD
pynep_cpu-0.1.dev9.dist-info/LICENSE
pynep_cpu-0.1.dev9.dist-info/WHEEL
pynep_cpu-0.1.dev9.dist-info/top_level.txt
pynep_cpu-0.1.dev9.dist-info/METADATA
